{
  "annotations": {
    "list": [
      {
        "builtIn": 1,
        "datasource": "-- Grafana --",
        "enable": true,
        "hide": true,
        "iconColor": "rgba(0, 211, 255, 1)",
        "name": "Annotations & Alerts",
        "type": "dashboard"
      },
      {
        "datasource": "Influx",
        "enable": true,
        "hide": false,
        "iconColor": "#c0c6be",
        "limit": 100,
        "name": "Global Events",
        "query": "select title, text from events where $timeFilter and realm =~ /$realm$/",
        "showIn": 0,
        "tags": [],
        "textColumn": "text",
        "type": "tags"
      }
    ]
  },
  "editable": true,
  "gnetId": null,
  "graphTooltip": 0,
  "id": 15,
  "iteration": 1626984445687,
  "links": [],
  "panels": [
    {
      "aliasColors": {},
      "bars": false,
      "dashLength": 10,
      "dashes": false,
      "datasource": "Influx",
      "editable": true,
      "error": false,
      "fieldConfig": {
        "defaults": {
          "links": []
        },
        "overrides": []
      },
      "fill": 1,
      "fillGradient": 0,
      "grid": {
        "leftLogBase": 1,
        "leftMax": null,
        "leftMin": null,
        "rightLogBase": 1,
        "rightMax": null,
        "rightMin": null
      },
      "gridPos": {
        "h": 7,
        "w": 24,
        "x": 0,
        "y": 0
      },
      "hiddenSeries": false,
      "id": 4,
      "isNew": true,
      "legend": {
        "avg": false,
        "current": false,
        "max": false,
        "min": false,
        "show": true,
        "total": false,
        "values": false
      },
      "lines": true,
      "linewidth": 2,
      "links": [],
      "nullPointMode": "connected",
      "options": {
        "alertThreshold": true
      },
      "percentage": false,
      "pluginVersion": "8.0.3",
      "pointradius": 5,
      "points": false,
      "renderer": "flot",
      "seriesOverrides": [],
      "spaceLength": 10,
      "stack": false,
      "steppedLine": false,
      "targets": [
        {
          "alias": "Update diff",
          "dsType": "influxdb",
          "groupBy": [
            {
              "params": [
                "$interval"
              ],
              "type": "time"
            },
            {
              "params": [
                "null"
              ],
              "type": "fill"
            }
          ],
          "measurement": "update_time_diff",
          "orderByTime": "ASC",
          "policy": "default",
          "query": "SELECT max(\"value\") FROM \"update_time_diff\" WHERE (\"realm\" =~ /$realm$/) AND $timeFilter GROUP BY time($interval) fill(null)",
          "rawQuery": false,
          "refId": "A",
          "resultFormat": "time_series",
          "select": [
            [
              {
                "params": [
                  "value"
                ],
                "type": "field"
              },
              {
                "params": [],
                "type": "max"
              }
            ]
          ],
          "tags": [
            {
              "key": "realm",
              "operator": "=~",
              "value": "/$realm$/"
            }
          ]
        }
      ],
      "thresholds": [],
      "timeFrom": null,
      "timeRegions": [],
      "timeShift": null,
      "title": "Update diff",
      "tooltip": {
        "msResolution": false,
        "shared": true,
        "sort": 0,
        "value_type": "cumulative"
      },
      "type": "graph",
      "x-axis": true,
      "xaxis": {
        "buckets": null,
        "mode": "time",
        "name": null,
        "show": true,
        "values": []
      },
      "y-axis": true,
      "y_formats": [
        "ms",
        "short"
      ],
      "yaxes": [
        {
          "format": "ms",
          "label": null,
          "logBase": 1,
          "max": null,
          "min": null,
          "show": true
        },
        {
          "format": "short",
          "label": null,
          "logBase": 1,
          "max": null,
          "min": null,
          "show": true
        }
      ],
      "yaxis": {
        "align": false,
        "alignLevel": null
      }
    },
    {
      "aliasColors": {},
      "bars": false,
      "dashLength": 10,
      "dashes": false,
      "datasource": null,
      "fieldConfig": {
        "defaults": {
          "links": []
        },
        "overrides": []
      },
      "fill": 1,
      "fillGradient": 0,
      "gridPos": {
        "h": 8,
        "w": 12,
        "x": 0,
        "y": 7
      },
      "hiddenSeries": false,
      "id": 6,
      "legend": {
        "alignAsTable": true,
        "avg": false,
        "current": false,
        "hideEmpty": false,
        "hideZero": true,
        "max": false,
        "min": false,
        "rightSide": true,
        "show": true,
        "total": false,
        "values": false
      },
      "lines": true,
      "linewidth": 2,
      "nullPointMode": "connected",
      "options": {
        "alertThreshold": true
      },
      "percentage": false,
      "pluginVersion": "8.0.3",
      "pointradius": 2,
      "points": false,
      "renderer": "flot",
      "seriesOverrides": [],
      "spaceLength": 10,
      "stack": false,
      "steppedLine": false,
      "targets": [
        {
          "alias": "Total",
          "groupBy": [
            {
              "params": [
                "$__interval"
              ],
              "type": "time"
            },
            {
              "params": [
                "0"
              ],
              "type": "fill"
            }
          ],
          "measurement": "world_update_time_total",
          "orderByTime": "ASC",
          "policy": "default",
          "query": "SELECT max(\"value\") FROM \"map_update_time_diff\" WHERE (\"realm\" =~ /^$realm$/) AND $timeFilter GROUP BY time($__interval), \"map_id\" fill(none)",
          "rawQuery": false,
          "refId": "B",
          "resultFormat": "time_series",
          "select": [
            [
              {
                "params": [
                  "value"
                ],
                "type": "field"
              },
              {
                "params": [],
                "type": "max"
              }
            ]
          ],
          "tags": [
            {
              "key": "realm",
              "operator": "=~",
              "value": "/^$realm$/"
            }
          ]
        },
        {
          "alias": "$tag_type",
          "groupBy": [
            {
              "params": [
                "$__interval"
              ],
              "type": "time"
            },
            {
              "params": [
                "type"
              ],
              "type": "tag"
            },
            {
              "params": [
                "0"
              ],
              "type": "fill"
            }
          ],
          "measurement": "world_update_time",
          "orderByTime": "ASC",
          "policy": "default",
          "query": "SELECT max(\"value\") FROM \"map_update_time_diff\" WHERE (\"realm\" =~ /^$realm$/) AND $timeFilter GROUP BY time($__interval), \"map_id\" fill(none)",
          "rawQuery": false,
          "refId": "C",
          "resultFormat": "time_series",
          "select": [
            [
              {
                "params": [
                  "value"
                ],
                "type": "field"
              },
              {
                "params": [],
                "type": "max"
              }
            ]
          ],
          "tags": [
            {
              "key": "realm",
              "operator": "=~",
              "value": "/^$realm$/"
            }
          ]
        }
      ],
      "thresholds": [],
      "timeFrom": null,
      "timeRegions": [],
      "timeShift": null,
      "title": "World Update - Split",
      "tooltip": {
        "shared": true,
        "sort": 0,
        "value_type": "individual"
      },
      "type": "graph",
      "xaxis": {
        "buckets": null,
        "mode": "time",
        "name": null,
        "show": true,
        "values": []
      },
      "yaxes": [
        {
          "format": "ms",
          "label": null,
          "logBase": 1,
          "max": null,
          "min": null,
          "show": true
        },
        {
          "format": "short",
          "label": null,
          "logBase": 1,
          "max": null,
          "min": null,
          "show": true
        }
      ],
      "yaxis": {
        "align": false,
        "alignLevel": null
      }
    },
    {
      "aliasColors": {},
      "bars": false,
      "dashLength": 10,
      "dashes": false,
      "datasource": null,
      "fieldConfig": {
        "defaults": {
          "links": []
        },
        "overrides": []
      },
      "fill": 10,
      "fillGradient": 0,
      "gridPos": {
        "h": 8,
        "w": 12,
        "x": 12,
        "y": 7
      },
      "hiddenSeries": false,
      "id": 7,
      "legend": {
        "alignAsTable": true,
        "avg": false,
        "current": false,
        "hideEmpty": false,
        "hideZero": true,
        "max": false,
        "min": false,
        "rightSide": true,
        "show": true,
        "total": false,
        "values": false
      },
      "lines": true,
      "linewidth": 0,
      "nullPointMode": "connected",
      "options": {
        "alertThreshold": true
      },
      "percentage": false,
      "pluginVersion": "8.0.3",
      "pointradius": 2,
      "points": false,
      "renderer": "flot",
      "seriesOverrides": [],
      "spaceLength": 10,
      "stack": true,
      "steppedLine": false,
      "targets": [
        {
          "alias": "$tag_type",
          "groupBy": [
            {
              "params": [
                "$__interval"
              ],
              "type": "time"
            },
            {
              "params": [
                "type"
              ],
              "type": "tag"
            },
            {
              "params": [
                "0"
              ],
              "type": "fill"
            }
          ],
          "measurement": "world_update_time",
          "orderByTime": "ASC",
          "policy": "default",
          "query": "SELECT max(\"value\") FROM \"map_update_time_diff\" WHERE (\"realm\" =~ /^$realm$/) AND $timeFilter GROUP BY time($__interval), \"map_id\" fill(none)",
          "rawQuery": false,
          "refId": "C",
          "resultFormat": "time_series",
          "select": [
            [
              {
                "params": [
                  "value"
                ],
                "type": "field"
              },
              {
                "params": [],
                "type": "max"
              }
            ]
          ],
          "tags": [
            {
              "key": "realm",
              "operator": "=~",
              "value": "/^$realm$/"
            },
            {
              "condition": "AND",
              "key": "parent_type",
              "operator": "!~",
              "value": "/./"
            }
          ]
        }
      ],
      "thresholds": [],
      "timeFrom": null,
      "timeRegions": [],
      "timeShift": null,
      "title": "World Update - Stacked",
      "tooltip": {
        "shared": true,
        "sort": 0,
        "value_type": "individual"
      },
      "type": "graph",
      "xaxis": {
        "buckets": null,
        "mode": "time",
        "name": null,
        "show": true,
        "values": []
      },
      "yaxes": [
        {
          "format": "ms",
          "label": null,
          "logBase": 1,
          "max": null,
          "min": null,
          "show": true
        },
        {
          "format": "short",
          "label": null,
          "logBase": 1,
          "max": null,
          "min": null,
          "show": true
        }
      ],
      "yaxis": {
        "align": false,
        "alignLevel": null
      }
    },
    {
      "aliasColors": {},
      "bars": false,
      "dashLength": 10,
      "dashes": false,
      "datasource": null,
      "fieldConfig": {
        "defaults": {
          "links": []
        },
        "overrides": []
      },
      "fill": 1,
      "fillGradient": 0,
      "gridPos": {
        "h": 8,
        "w": 12,
        "x": 0,
        "y": 15
      },
      "hiddenSeries": false,
      "id": 2,
      "legend": {
        "alignAsTable": true,
        "avg": false,
        "current": false,
        "hideEmpty": false,
        "hideZero": true,
        "max": false,
        "min": false,
        "rightSide": true,
        "show": true,
        "total": false,
        "values": false
      },
      "lines": true,
      "linewidth": 2,
      "nullPointMode": "connected",
      "options": {
        "alertThreshold": true
      },
      "percentage": false,
      "pluginVersion": "8.0.3",
      "pointradius": 2,
      "points": false,
      "renderer": "flot",
      "seriesOverrides": [],
      "spaceLength": 10,
      "stack": false,
      "steppedLine": false,
      "targets": [
        {
          "alias": "Map $tag_map_id",
          "groupBy": [
            {
              "params": [
                "$__interval"
              ],
              "type": "time"
            },
            {
              "params": [
                "map_id"
              ],
              "type": "tag"
            },
            {
              "params": [
                "none"
              ],
              "type": "fill"
            }
          ],
          "measurement": "map_update_time_diff",
          "orderByTime": "ASC",
          "policy": "default",
          "query": "SELECT max(\"value\") FROM \"map_update_time_diff\" WHERE (\"realm\" =~ /^$realm$/) AND $timeFilter GROUP BY time($__interval), \"map_id\" fill(none)",
          "rawQuery": false,
          "refId": "A",
          "resultFormat": "time_series",
          "select": [
            [
              {
                "params": [
                  "value"
                ],
                "type": "field"
              },
              {
                "params": [],
                "type": "max"
              }
            ]
          ],
          "tags": [
            {
              "key": "realm",
              "operator": "=~",
              "value": "/^$realm$/"
            }
          ]
        }
      ],
      "thresholds": [],
      "timeFrom": null,
      "timeRegions": [],
      "timeShift": null,
      "title": "Map update - Split",
      "tooltip": {
        "shared": true,
        "sort": 0,
        "value_type": "individual"
      },
      "type": "graph",
      "xaxis": {
        "buckets": null,
        "mode": "time",
        "name": null,
        "show": true,
        "values": []
      },
      "yaxes": [
        {
          "format": "ms",
          "label": null,
          "logBase": 1,
          "max": null,
          "min": null,
          "show": true
        },
        {
          "format": "short",
          "label": null,
          "logBase": 1,
          "max": null,
          "min": null,
          "show": true
        }
      ],
      "yaxis": {
        "align": false,
        "alignLevel": null
      }
    },
    {
      "aliasColors": {},
      "bars": false,
      "dashLength": 10,
      "dashes": false,
      "datasource": null,
      "fieldConfig": {
        "defaults": {
          "links": []
        },
        "overrides": []
      },
      "fill": 10,
      "fillGradient": 0,
      "gridPos": {
        "h": 8,
        "w": 12,
        "x": 12,
        "y": 15
      },
      "hiddenSeries": false,
      "id": 5,
      "legend": {
        "alignAsTable": true,
        "avg": false,
        "current": false,
        "hideEmpty": false,
        "hideZero": true,
        "max": false,
        "min": false,
        "rightSide": true,
        "show": true,
        "total": false,
        "values": false
      },
      "lines": true,
      "linewidth": 0,
      "nullPointMode": "connected",
      "options": {
        "alertThreshold": true
      },
      "percentage": false,
      "pluginVersion": "8.0.3",
      "pointradius": 2,
      "points": false,
      "renderer": "flot",
      "seriesOverrides": [],
      "spaceLength": 10,
      "stack": true,
      "steppedLine": false,
      "targets": [
        {
          "alias": "Map $tag_map_id",
          "groupBy": [
            {
              "params": [
                "$__interval"
              ],
              "type": "time"
            },
            {
              "params": [
                "map_id"
              ],
              "type": "tag"
            },
            {
              "params": [
                "none"
              ],
              "type": "fill"
            }
          ],
          "measurement": "map_update_time_diff",
          "orderByTime": "ASC",
          "policy": "default",
          "query": "SELECT max(\"value\") FROM \"map_update_time_diff\" WHERE (\"realm\" =~ /^$realm$/) AND $timeFilter GROUP BY time($__interval), \"map_id\" fill(none)",
          "rawQuery": false,
          "refId": "A",
          "resultFormat": "time_series",
          "select": [
            [
              {
                "params": [
                  "value"
                ],
                "type": "field"
              },
              {
                "params": [],
                "type": "max"
              }
            ]
          ],
          "tags": [
            {
              "key": "realm",
              "operator": "=~",
              "value": "/^$realm$/"
            }
          ]
        }
      ],
      "thresholds": [],
      "timeFrom": null,
      "timeRegions": [],
      "timeShift": null,
      "title": "Map update - Stacked",
      "tooltip": {
        "shared": true,
        "sort": 0,
        "value_type": "individual"
      },
      "type": "graph",
      "xaxis": {
        "buckets": null,
        "mode": "time",
        "name": null,
        "show": true,
        "values": []
      },
      "yaxes": [
        {
          "format": "ms",
          "label": null,
          "logBase": 1,
          "max": null,
          "min": null,
          "show": true
        },
        {
          "format": "short",
          "label": null,
          "logBase": 1,
          "max": null,
          "min": null,
          "show": true
        }
      ],
      "yaxis": {
        "align": false,
        "alignLevel": null
      }
    },
    {
      "aliasColors": {},
      "bars": false,
      "dashLength": 10,
      "dashes": false,
      "datasource": null,
      "fieldConfig": {
        "defaults": {
          "links": []
        },
        "overrides": []
      },
      "fill": 1,
      "fillGradient": 0,
      "gridPos": {
        "h": 8,
        "w": 12,
        "x": 0,
        "y": 23
      },
      "hiddenSeries": false,
      "id": 9,
      "legend": {
        "alignAsTable": true,
        "avg": false,
        "current": false,
        "hideEmpty": false,
        "hideZero": true,
        "max": true,
        "min": false,
        "rightSide": true,
        "show": true,
        "sort": "max",
        "sortDesc": true,
        "total": false,
        "values": true
      },
      "lines": true,
      "linewidth": 2,
      "nullPointMode": "connected",
      "options": {
        "alertThreshold": true
      },
      "percentage": false,
      "pluginVersion": "8.0.3",
      "pointradius": 2,
      "points": false,
      "renderer": "flot",
      "seriesOverrides": [],
      "spaceLength": 10,
      "stack": false,
      "steppedLine": false,
      "targets": [
        {
          "alias": "Account ID $tag_account_id",
          "groupBy": [
            {
              "params": [
                "$__interval"
              ],
              "type": "time"
            },
            {
              "params": [
                "account_id"
              ],
              "type": "tag"
            },
            {
              "params": [
                "none"
              ],
              "type": "fill"
            }
          ],
          "measurement": "world_update_sessions_time",
          "orderByTime": "ASC",
          "policy": "default",
          "query": "SELECT max(\"value\") FROM \"map_update_time_diff\" WHERE (\"realm\" =~ /^$realm$/) AND $timeFilter GROUP BY time($__interval), \"map_id\" fill(none)",
          "rawQuery": false,
          "refId": "A",
          "resultFormat": "time_series",
          "select": [
            [
              {
                "params": [
                  "value"
                ],
                "type": "field"
              },
              {
                "params": [],
                "type": "max"
              }
            ]
          ],
          "tags": [
            {
              "key": "realm",
              "operator": "=~",
              "value": "/^$realm$/"
            }
          ]
        }
      ],
      "thresholds": [],
      "timeFrom": null,
      "timeRegions": [],
      "timeShift": null,
      "title": "Update sessions - Split",
      "tooltip": {
        "shared": true,
        "sort": 2,
        "value_type": "individual"
      },
      "type": "graph",
      "xaxis": {
        "buckets": null,
        "mode": "time",
        "name": null,
        "show": true,
        "values": []
      },
      "yaxes": [
        {
          "format": "ms",
          "label": null,
          "logBase": 1,
          "max": null,
          "min": null,
          "show": true
        },
        {
          "format": "short",
          "label": null,
          "logBase": 1,
          "max": null,
          "min": null,
          "show": true
        }
      ],
      "yaxis": {
        "align": false,
        "alignLevel": null
      }
    },
    {
      "aliasColors": {},
      "bars": true,
      "dashLength": 10,
      "dashes": false,
      "datasource": null,
      "fieldConfig": {
        "defaults": {
          "links": []
        },
        "overrides": []
      },
      "fill": 1,
      "fillGradient": 0,
      "gridPos": {
        "h": 8,
        "w": 12,
        "x": 12,
        "y": 23
      },
      "hiddenSeries": false,
      "id": 11,
      "legend": {
        "alignAsTable": true,
        "avg": false,
        "current": false,
        "hideEmpty": true,
        "hideZero": true,
        "max": true,
        "min": false,
        "rightSide": true,
        "show": true,
        "sort": "max",
        "sortDesc": true,
        "total": false,
        "values": true
      },
      "lines": false,
      "linewidth": 2,
      "nullPointMode": "null",
      "options": {
        "alertThreshold": true
      },
      "percentage": false,
      "pluginVersion": "8.0.3",
      "pointradius": 2,
      "points": true,
      "renderer": "flot",
      "seriesOverrides": [],
      "spaceLength": 10,
      "stack": false,
      "steppedLine": false,
      "targets": [
        {
          "alias": "Opcode $tag_opcode",
          "groupBy": [
            {
              "params": [
                "$__interval"
              ],
              "type": "time"
            },
            {
              "params": [
                "opcode"
              ],
              "type": "tag"
            },
            {
              "params": [
                "null"
              ],
              "type": "fill"
            }
          ],
          "measurement": "worldsession_update_opcode_time",
          "orderByTime": "ASC",
          "policy": "default",
          "query": "SELECT max(\"value\") FROM \"worldsession_update_opcode_time\" WHERE (\"realm\" =~ /^$realm$/) AND $timeFilter GROUP BY time($__interval), \"opcode\" fill(null)",
          "rawQuery": false,
          "refId": "A",
          "resultFormat": "time_series",
          "select": [
            [
              {
                "params": [
                  "value"
                ],
                "type": "field"
              },
              {
                "params": [],
                "type": "max"
              }
            ]
          ],
          "tags": [
            {
              "key": "realm",
              "operator": "=~",
              "value": "/^$realm$/"
            }
          ]
        }
      ],
      "thresholds": [],
      "timeFrom": null,
      "timeRegions": [],
      "timeShift": null,
      "title": "Opcode handlers - Split",
      "tooltip": {
        "shared": false,
        "sort": 2,
        "value_type": "individual"
      },
      "type": "graph",
      "xaxis": {
        "buckets": null,
        "mode": "time",
        "name": null,
        "show": true,
        "values": []
      },
      "yaxes": [
        {
          "format": "ms",
          "label": null,
          "logBase": 1,
          "max": null,
          "min": null,
          "show": true
        },
        {
          "format": "short",
          "label": null,
          "logBase": 1,
          "max": null,
          "min": null,
          "show": true
        }
      ],
      "yaxis": {
        "align": false,
        "alignLevel": null
      }
    },
    {
      "aliasColors": {},
      "bars": false,
      "dashLength": 10,
      "dashes": false,
      "datasource": null,
      "fieldConfig": {
        "defaults": {
          "links": []
        },
        "overrides": []
      },
      "fill": 5,
      "fillGradient": 0,
      "gridPos": {
        "h": 8,
        "w": 12,
        "x": 0,
        "y": 31
      },
      "hiddenSeries": false,
      "id": 13,
      "legend": {
        "alignAsTable": true,
        "avg": false,
        "current": false,
        "hideEmpty": false,
        "hideZero": true,
        "max": false,
        "min": false,
        "rightSide": true,
        "show": true,
        "total": false,
        "values": false
      },
      "lines": true,
      "linewidth": 1,
      "nullPointMode": "null",
      "options": {
        "alertThreshold": true
      },
      "percentage": false,
      "pluginVersion": "8.0.3",
      "pointradius": 2,
      "points": false,
      "renderer": "flot",
      "seriesOverrides": [],
      "spaceLength": 10,
      "stack": false,
      "steppedLine": false,
      "targets": [
        {
          "alias": "Map $tag_map_id Instance $tag_map_instanceid",
          "groupBy": [
            {
              "params": [
                "$__interval"
              ],
              "type": "time"
            },
            {
              "params": [
                "map_id"
              ],
              "type": "tag"
            },
            {
              "params": [
                "map_instanceid"
              ],
              "type": "tag"
            },
            {
              "params": [
                "none"
              ],
              "type": "fill"
            }
          ],
          "measurement": "map_creatures",
          "orderByTime": "ASC",
          "policy": "default",
          "refId": "A",
          "resultFormat": "time_series",
          "select": [
            [
              {
                "params": [
                  "value"
                ],
                "type": "field"
              },
              {
                "params": [],
                "type": "mean"
              }
            ]
          ],
          "tags": [
            {
              "key": "realm",
              "operator": "=~",
              "value": "/^$realm$/"
            }
          ]
        }
      ],
      "thresholds": [],
      "timeFrom": null,
      "timeRegions": [],
      "timeShift": null,
      "title": "Creatures",
      "tooltip": {
        "shared": true,
        "sort": 0,
        "value_type": "individual"
      },
      "type": "graph",
      "xaxis": {
        "buckets": null,
        "mode": "time",
        "name": null,
        "show": true,
        "values": []
      },
      "yaxes": [
        {
          "format": "short",
          "label": null,
          "logBase": 1,
          "max": null,
          "min": null,
          "show": true
        },
        {
          "format": "short",
          "label": null,
          "logBase": 1,
          "max": null,
          "min": null,
          "show": true
        }
      ],
      "yaxis": {
        "align": false,
        "alignLevel": null
      }
    },
    {
      "aliasColors": {},
      "bars": false,
      "dashLength": 10,
      "dashes": false,
      "datasource": null,
      "fieldConfig": {
        "defaults": {
          "links": []
        },
        "overrides": []
      },
      "fill": 5,
      "fillGradient": 0,
      "gridPos": {
        "h": 8,
        "w": 12,
        "x": 12,
        "y": 31
      },
      "hiddenSeries": false,
      "id": 15,
      "legend": {
        "alignAsTable": true,
        "avg": false,
        "current": false,
        "hideEmpty": false,
        "hideZero": true,
        "max": false,
        "min": false,
        "rightSide": true,
        "show": true,
        "total": false,
        "values": false
      },
      "lines": true,
      "linewidth": 1,
      "nullPointMode": "null",
      "options": {
        "alertThreshold": true
      },
      "percentage": false,
      "pluginVersion": "8.0.3",
      "pointradius": 2,
      "points": false,
      "renderer": "flot",
      "seriesOverrides": [],
      "spaceLength": 10,
      "stack": false,
      "steppedLine": false,
      "targets": [
        {
          "alias": "Map $tag_map_id Instance $tag_map_instanceid",
          "groupBy": [
            {
              "params": [
                "$__interval"
              ],
              "type": "time"
            },
            {
              "params": [
                "map_id"
              ],
              "type": "tag"
            },
            {
              "params": [
                "map_instanceid"
              ],
              "type": "tag"
            },
            {
              "params": [
                "none"
              ],
              "type": "fill"
            }
          ],
          "measurement": "map_gameobjects",
          "orderByTime": "ASC",
          "policy": "default",
          "refId": "A",
          "resultFormat": "time_series",
          "select": [
            [
              {
                "params": [
                  "value"
                ],
                "type": "field"
              },
              {
                "params": [],
                "type": "mean"
              }
            ]
          ],
          "tags": [
            {
              "key": "realm",
              "operator": "=~",
              "value": "/^$realm$/"
            }
          ]
        }
      ],
      "thresholds": [],
      "timeFrom": null,
      "timeRegions": [],
      "timeShift": null,
      "title": "Gameobjects",
      "tooltip": {
        "shared": true,
        "sort": 0,
        "value_type": "individual"
      },
      "type": "graph",
      "xaxis": {
        "buckets": null,
        "mode": "time",
        "name": null,
        "show": true,
        "values": []
      },
      "yaxes": [
        {
          "format": "short",
          "label": null,
          "logBase": 1,
          "max": null,
          "min": null,
          "show": true
        },
        {
          "format": "short",
          "label": null,
          "logBase": 1,
          "max": null,
          "min": null,
          "show": true
        }
      ],
      "yaxis": {
        "align": false,
        "alignLevel": null
      }
    },
    {
      "aliasColors": {},
      "bars": false,
      "dashLength": 10,
      "dashes": false,
      "datasource": null,
      "fill": 1,
      "fillGradient": 0,
      "gridPos": {
        "h": 8,
        "w": 12,
        "x": 0,
        "y": 39
      },
      "hiddenSeries": false,
      "id": 17,
      "legend": {
        "avg": false,
        "current": false,
        "max": false,
        "min": false,
        "show": true,
        "total": false,
        "values": false
      },
      "lines": true,
      "linewidth": 2,
      "nullPointMode": "connected",
      "options": {
        "alertThreshold": true
      },
      "percentage": false,
      "pluginVersion": "8.0.3",
      "pointradius": 2,
      "points": false,
      "renderer": "flot",
      "seriesOverrides": [],
      "spaceLength": 10,
      "stack": false,
      "steppedLine": false,
      "targets": [
        {
          "alias": "Login DB",
          "groupBy": [
            {
              "params": [
                "$__interval"
              ],
              "type": "time"
            },
            {
              "params": [
                "null"
              ],
              "type": "fill"
            }
          ],
          "measurement": "db_queue_login",
          "orderByTime": "ASC",
          "policy": "default",
          "refId": "A",
          "resultFormat": "time_series",
          "select": [
            [
              {
                "params": [
                  "value"
                ],
                "type": "field"
              },
              {
                "params": [],
                "type": "max"
              }
            ]
          ],
          "tags": [
            {
              "key": "realm",
              "operator": "=~",
              "value": "/^$realm$/"
            }
          ]
        },
        {
          "alias": "Character DB",
          "groupBy": [
            {
              "params": [
                "$__interval"
              ],
              "type": "time"
            },
            {
              "params": [
                "null"
              ],
              "type": "fill"
            }
          ],
          "hide": false,
          "measurement": "db_queue_character",
          "orderByTime": "ASC",
          "policy": "default",
          "refId": "B",
          "resultFormat": "time_series",
          "select": [
            [
              {
                "params": [
                  "value"
                ],
                "type": "field"
              },
              {
                "params": [],
                "type": "max"
              }
            ]
          ],
          "tags": [
            {
              "key": "realm",
              "operator": "=~",
              "value": "/^$realm$/"
            }
          ]
        },
        {
          "alias": "World DB",
          "groupBy": [
            {
              "params": [
                "$__interval"
              ],
              "type": "time"
            },
            {
              "params": [
                "null"
              ],
              "type": "fill"
            }
          ],
          "hide": false,
          "measurement": "db_queue_world",
          "orderByTime": "ASC",
          "policy": "default",
          "refId": "C",
          "resultFormat": "time_series",
          "select": [
            [
              {
                "params": [
                  "value"
                ],
                "type": "field"
              },
              {
                "params": [],
                "type": "max"
              }
            ]
          ],
          "tags": [
            {
              "key": "realm",
              "operator": "=~",
              "value": "/^$realm$/"
            }
          ]
        }
      ],
      "thresholds": [],
      "timeFrom": null,
      "timeRegions": [],
      "timeShift": null,
      "title": "Database queue",
      "tooltip": {
        "shared": true,
        "sort": 0,
        "value_type": "individual"
      },
      "type": "graph",
      "xaxis": {
        "buckets": null,
        "mode": "time",
        "name": null,
        "show": true,
        "values": []
      },
      "yaxes": [
        {
          "$$hashKey": "object:102",
          "format": "short",
          "label": null,
          "logBase": 1,
          "max": null,
          "min": null,
          "show": true
        },
        {
          "$$hashKey": "object:103",
          "format": "short",
          "label": null,
          "logBase": 1,
          "max": null,
          "min": null,
          "show": true
        }
      ],
      "yaxis": {
        "align": false,
        "alignLevel": null
      }
    }
  ],
  "refresh": "1m",
  "schemaVersion": 30,
  "style": "dark",
  "tags": [],
  "templating": {
    "list": [
      {
        "allValue": null,
        "current": {
          "selected": true,
          "text": "Trinity",
          "value": "Trinity"
        },
        "datasource": "Influx",
        "definition": "show tag values from events with key = realm",
        "description": null,
        "error": null,
        "hide": 0,
        "includeAll": false,
        "label": null,
        "multi": false,
        "name": "realm",
        "options": [],
        "query": "show tag values from events with key = realm",
        "refresh": 1,
        "regex": "",
        "skipUrlSync": false,
        "sort": 0,
        "tagValuesQuery": "",
        "tagsQuery": "",
        "type": "query",
        "useTags": false
      }
    ]
  },
  "time": {
    "from": "now-1h",
    "to": "now"
  },
  "timepicker": {
    "refresh_intervals": [
      "10s",
      "30s",
      "1m",
      "5m",
      "15m",
      "30m",
      "1h",
      "2h",
      "1d"
    ]
  },
  "timezone": "",
  "title": "Performance profiling",
  "uid": "IRRL03nMk",
  "version": 9
}